Metadata-Version: 1.1
Name: django-multifield-clean
Version: 0.0.1
Summary: TODO
Home-page: TODO
Author: Antoine Humeau
Author-email: humeau.antoine@gmail.com
License: TODO
Platform: UNKNOWN
Classifier: Framework :: Django
Classifier: Programming Language :: Python
Classifier: Programming Language :: Python :: 3
Classifier: License :: OSI Approved :: MIT License
